WeiXueyuanTkinterJiaocheng/README.md
WeiXueyuanTkinterJiaocheng/__init__.py
WeiXueyuanTkinterJiaocheng/__main__.py
WeiXueyuanTkinterJiaocheng/file.epub
WeiXueyuanTkinterJiaocheng/index.html
WeiXueyuanTkinterJiaocheng/css/__init__.py
WeiXueyuanTkinterJiaocheng/css/annotations.css
WeiXueyuanTkinterJiaocheng/css/main.css
WeiXueyuanTkinterJiaocheng/css/normalize.css
WeiXueyuanTkinterJiaocheng/css/popup.css
WeiXueyuanTkinterJiaocheng/font/__init__.py
WeiXueyuanTkinterJiaocheng/font/fontello.eot
WeiXueyuanTkinterJiaocheng/font/fontello.svg
WeiXueyuanTkinterJiaocheng/font/fontello.ttf
WeiXueyuanTkinterJiaocheng/font/fontello.woff
WeiXueyuanTkinterJiaocheng/img/__init__.py
WeiXueyuanTkinterJiaocheng/img/annotator-glyph-sprite.png
WeiXueyuanTkinterJiaocheng/img/annotator-icon-sprite.png
WeiXueyuanTkinterJiaocheng/img/apple-touch-icon.png
WeiXueyuanTkinterJiaocheng/img/cancelfullscreen.png
WeiXueyuanTkinterJiaocheng/img/close.png
WeiXueyuanTkinterJiaocheng/img/fullscreen.png
WeiXueyuanTkinterJiaocheng/img/loader.gif
WeiXueyuanTkinterJiaocheng/img/menu-icon.png
WeiXueyuanTkinterJiaocheng/img/save.png
WeiXueyuanTkinterJiaocheng/img/saved.png
WeiXueyuanTkinterJiaocheng/img/settings-s.png
WeiXueyuanTkinterJiaocheng/img/settings.png
WeiXueyuanTkinterJiaocheng/img/star.png
WeiXueyuanTkinterJiaocheng/js/__init__.py
WeiXueyuanTkinterJiaocheng/js/epub.js
WeiXueyuanTkinterJiaocheng/js/epub.min.js
WeiXueyuanTkinterJiaocheng/js/epub.min.map
WeiXueyuanTkinterJiaocheng/js/hooks.min.js
WeiXueyuanTkinterJiaocheng/js/hooks.min.map
WeiXueyuanTkinterJiaocheng/js/reader.js
WeiXueyuanTkinterJiaocheng/js/reader.js.map
WeiXueyuanTkinterJiaocheng/js/reader.min.js
WeiXueyuanTkinterJiaocheng/js/reader.min.map
WeiXueyuanTkinterJiaocheng/js/hooks/__init__.py
WeiXueyuanTkinterJiaocheng/js/hooks/extensions/__init__.py
WeiXueyuanTkinterJiaocheng/js/hooks/extensions/highlight.js
WeiXueyuanTkinterJiaocheng/js/libs/__init__.py
WeiXueyuanTkinterJiaocheng/js/libs/jquery.min.js
wei_xueyuan_tkinter_jiaocheng-2024.3.6.0.dist-info/METADATA
wei_xueyuan_tkinter_jiaocheng-2024.3.6.0.dist-info/WHEEL
wei_xueyuan_tkinter_jiaocheng-2024.3.6.0.dist-info/entry_points.txt
wei_xueyuan_tkinter_jiaocheng-2024.3.6.0.dist-info/top_level.txt
wei_xueyuan_tkinter_jiaocheng-2024.3.6.0.dist-info/RECORD
